{"0": {"represent_word": "sits on", "words": ["sit on", "sits on", "stacked on", "sits with", "resting on", "leaning on", "placed on", "siting on", "rests on", "writing on", "being prepared on", "prepared on", "seated on", "perched on", "displayed on"], "represent_word_sim": 0.9757788814269555}, "1": {"represent_word": "filled with", "words": ["filled with", "surrounded by", "filled", "full of", "is filled with", "topped with", "loaded with", "bowls of"], "represent_word_sim": 0.9777825293162703}, "2": {"represent_word": "riding", "words": ["riding"], "represent_word_sim": 1.0000000105224829}, "3": {"represent_word": "walking", "words": ["walking with", "walking", "is walking", "walking near", "walking through", "walking next to", "walking past"], "represent_word_sim": 0.9689151305857898}, "4": {"represent_word": "playing with", "words": ["playing", "is playing", "playing on", "playing with", "are playing", "playing in", "is playing with"], "represent_word_sim": 0.9701028343392211}, "5": {"represent_word": "is parked near", "words": ["is parked by", "parked near", "is parked near"], "represent_word_sim": 0.9884423481730511}, "6": {"represent_word": "standing in", "words": ["is standing in", "standing in", "stand in", "are standing in", "are cooking in", "standing around in", "while standing in", "gathered in"], "represent_word_sim": 0.9851499600935861}, "7": {"represent_word": "is shown in", "words": ["is full of", "is shown with", "shown with", "is shown in", "shown in", "done in", "displayed in", "sinks in", "placed in", "is shown on", "shown on", "used as"], "represent_word_sim": 0.9853154547712789}, "8": {"represent_word": "cut", "words": ["to cut", "cut"], "represent_word_sim": 0.9880699102836379}, "9": {"represent_word": "looking into", "words": ["looking in", "looking", "looking into"], "represent_word_sim": 0.9797977227870635}, "10": {"represent_word": "looking at", "words": ["looking over", "looking at", "staring at", "getting ready for", "looking down at", "is looking at", "are looking at", "looking for", "looks at", "look at", "looking up at"], "represent_word_sim": 0.989266315986512}, "11": {"represent_word": "provide", "words": ["provide", "to provide"], "represent_word_sim": 0.9903642298912969}, "12": {"represent_word": "flies in", "words": ["flies through", "flies in"], "represent_word_sim": 0.9875674409530085}, "13": {"represent_word": "prop", "words": ["prop"], "represent_word_sim": 1.0000000268120177}, "14": {"represent_word": "sitting next to", "words": ["next to", "is next to", "sits next to", "sitting next to", "leading to", "sitting under", "shown next to", "are next to"], "represent_word_sim": 0.9820095466412117}, "15": {"represent_word": "flying in", "words": ["flying in", "is flying in", "flying high in", "flying through", "fly in", "are flying in", "is flying through", "flying across"], "represent_word_sim": 0.988008867276669}, "16": {"represent_word": "standing around", "words": ["around", "gathered around", "standing around", "stand around", "sitting around", "are standing around"], "represent_word_sim": 0.9810202512614034}, "17": {"represent_word": "pulling", "words": ["pulling", "pulled by", "is pulling"], "represent_word_sim": 0.9746275511020056}, "18": {"represent_word": "wearing", "words": ["wearing", "is wearing", "while wearing"], "represent_word_sim": 0.9813783305239256}, "19": {"represent_word": "is equipped with", "words": ["is equipped with", "equipped with", "being remodeled with", "remodeled with"], "represent_word_sim": 0.9794303814307225}, "20": {"represent_word": "to prepare", "words": ["to prepare"], "represent_word_sim": 0.9999999780038878}, "21": {"represent_word": "standing with", "words": ["is standing at", "is standing with", "standing with", "sitting with", "is standing by", "standing by", "is standing near"], "represent_word_sim": 0.9748855471079774}, "22": {"represent_word": "is sitting in", "words": ["sit in", "sitting in", "is riding in", "posing in", "sitting inside", "sits in", "floating in", "sleeping in", "is sitting in", "are sitting in", "sitting by", "lying in", "while sitting in", "close up of", "there is", "resting in", "sitting outside of"], "represent_word_sim": 0.983907202669707}, "23": {"represent_word": "carrying", "words": ["carrying", "is carrying", "carries"], "represent_word_sim": 0.9786645113162937}, "24": {"represent_word": "hanging", "words": ["hanging in", "hanging", "hanging from", "hanging over", "hanging above"], "represent_word_sim": 0.9717193290238237}, "25": {"represent_word": "sink with", "words": ["sink with"], "represent_word_sim": 0.9999999712653042}, "26": {"represent_word": "eaten", "words": ["eaten"], "represent_word_sim": 0.9999999838057418}, "27": {"represent_word": "parked outside of", "words": ["outside of", "parked outside of", "outside", "parked outside", "is parked outside"], "represent_word_sim": 0.9820052433379501}, "28": {"represent_word": "to see", "words": ["see", "to see"], "represent_word_sim": 0.9642199273459892}, "29": {"represent_word": "leaning against", "words": ["leans on", "leaning against", "against", "leans against", "leaning up against", "leaning over"], "represent_word_sim": 0.984823615848983}, "30": {"represent_word": "riding down", "words": ["traveling down", "riding down", "is riding down", "are riding down"], "represent_word_sim": 0.988243171278913}, "31": {"represent_word": "folded", "words": ["folded"], "represent_word_sim": 1.0000000331408312}, "32": {"represent_word": "racing", "words": ["racing", "racing on"], "represent_word_sim": 0.9774500112273996}, "33": {"represent_word": "driving down", "words": ["driving on", "driving through", "driving down", "is driving down", "driving in"], "represent_word_sim": 0.9762316042812202}, "34": {"represent_word": "walking on", "words": ["walking on", "walking in", "walking along", "walking by", "walks on", "is walking on", "walking around", "walking into", "traveling on"], "represent_word_sim": 0.9832581978489342}, "35": {"represent_word": "walking down", "words": ["are walking down", "walking down", "walks down", "walk down", "walking across", "is walking down"], "represent_word_sim": 0.9902076142199793}, "36": {"represent_word": "is taking", "words": ["is taking", "to take"], "represent_word_sim": 0.9768595760708719}, "37": {"represent_word": "cutting", "words": ["cutting", "cutting into", "is cutting", "cutting up"], "represent_word_sim": 0.9816350825234469}, "38": {"represent_word": "sinks", "words": ["sinks"], "represent_word_sim": 0.999999983080912}, "39": {"represent_word": "driving", "words": ["driving", "is driving"], "represent_word_sim": 0.9869147982688009}, "40": {"represent_word": "posing for", "words": ["poses for", "posing for", "is posing for", "pose for"], "represent_word_sim": 0.9851326018985668}, "41": {"represent_word": "counter", "words": ["counter"], "represent_word_sim": 0.9999999799452521}, "42": {"represent_word": "displaying", "words": ["displaying"], "represent_word_sim": 1.0000000457561231}, "43": {"represent_word": "eats", "words": ["eating", "eats"], "represent_word_sim": 0.9793474233322723}, "44": {"represent_word": "depicting", "words": ["depicting"], "represent_word_sim": 1.0000000222465446}, "45": {"represent_word": "doing", "words": ["doing", "is doing"], "represent_word_sim": 0.987561837704472}, "46": {"represent_word": "hold", "words": ["holds", "hold"], "represent_word_sim": 0.9754536255084101}, "47": {"represent_word": "standing beside", "words": ["beside", "standing beside", "sitting beside", "is standing beside"], "represent_word_sim": 0.9793176903317068}, "48": {"represent_word": "make", "words": ["makes", "to make", "make"], "represent_word_sim": 0.9817098691418681}, "49": {"represent_word": "slicing", "words": ["slicing"], "represent_word_sim": 0.999999981722851}, "50": {"represent_word": "drinking", "words": ["drinking"], "represent_word_sim": 1.0000000003416127}, "51": {"represent_word": "handle", "words": ["handle"], "represent_word_sim": 0.9999999718487544}, "52": {"represent_word": "thru", "words": ["thru"], "represent_word_sim": 1.0000000363430464}, "53": {"represent_word": "serve", "words": ["serving", "serve"], "represent_word_sim": 0.9713977295904237}, "54": {"represent_word": "amongst", "words": ["amongst", "among"], "represent_word_sim": 0.9828197843009395}, "55": {"represent_word": "laying on", "words": ["laying on", "is laying on", "lays on", "laying next to", "laying in", "laying down in", "laying under", "laying down on", "is laying in", "laying"], "represent_word_sim": 0.984269772464931}, "56": {"represent_word": "reflecting", "words": ["reflecting", "reflects"], "represent_word_sim": 0.9786309991952928}, "57": {"represent_word": "waiting at", "words": ["waiting for", "waiting at", "waiting on", "stopped at", "waiting in"], "represent_word_sim": 0.9766844907481526}, "58": {"represent_word": "lined up on", "words": ["lined up in", "lined with", "stack of", "lined up on", "hooked up to"], "represent_word_sim": 0.9761589366618496}, "59": {"represent_word": "is watching", "words": ["watching", "are watching", "is watching"], "represent_word_sim": 0.9719269918764558}, "60": {"represent_word": "fashioned", "words": ["fashioned"], "represent_word_sim": 1.0000000682423158}, "61": {"represent_word": "stop", "words": ["stop"], "represent_word_sim": 1.0000000090726189}, "62": {"represent_word": "jumping", "words": ["jumping"], "represent_word_sim": 1.0000000716135389}, "63": {"represent_word": "flying over", "words": ["is flying over", "flying over", "flying low over", "flies over", "flying above"], "represent_word_sim": 0.9877156771901197}, "64": {"represent_word": "cross", "words": ["cross"], "represent_word_sim": 0.999999985672263}, "65": {"represent_word": "towards", "words": ["towards", "toward", "walking towards"], "represent_word_sim": 0.9742642817610241}, "66": {"represent_word": "parked on", "words": ["parked by", "parked next to", "parked with", "parked at", "parked against", "parked", "parked on", "are parked on", "parked along", "parked beside", "parked under", "parked inside"], "represent_word_sim": 0.979950766834951}, "67": {"represent_word": "tossing", "words": ["tossing"], "represent_word_sim": 1.0000000120468973}, "68": {"represent_word": "putting", "words": ["putting", "is putting"], "represent_word_sim": 0.9872492111663437}, "69": {"represent_word": "towing", "words": ["towing"], "represent_word_sim": 1.0000000079491695}, "70": {"represent_word": "catch", "words": ["to catch", "catch"], "represent_word_sim": 0.9879597613008413}, "71": {"represent_word": "framed", "words": ["framed"], "represent_word_sim": 1.00000001317703}, "72": {"represent_word": "uses", "words": ["uses", "use"], "represent_word_sim": 0.9664364138948269}, "73": {"represent_word": "underneath", "words": ["beneath", "underneath", "sitting underneath"], "represent_word_sim": 0.9838543166694345}, "74": {"represent_word": "sized", "words": ["sized"], "represent_word_sim": 1.00000004317765}, "75": {"represent_word": "run", "words": ["run"], "represent_word_sim": 1.0000000581742063}, "76": {"represent_word": "loading", "words": ["loading"], "represent_word_sim": 0.9999999390442841}, "77": {"represent_word": "sliding", "words": ["sliding"], "represent_word_sim": 0.9999999499664778}, "78": {"represent_word": "fixing", "words": ["fixing"], "represent_word_sim": 0.9999999785546124}, "79": {"represent_word": "missing", "words": ["missing", "is missing"], "represent_word_sim": 0.9851675068503508}, "80": {"represent_word": "look like", "words": ["like", "looks like", "shaped like", "to look like", "look like"], "represent_word_sim": 0.9713757863108567}, "81": {"represent_word": "gives", "words": ["giving", "gives"], "represent_word_sim": 0.9712764465792614}, "82": {"represent_word": "licking", "words": ["licking"], "represent_word_sim": 1.0000000156892133}, "83": {"represent_word": "washing", "words": ["is washing", "washing"], "represent_word_sim": 0.9864871056291016}, "84": {"represent_word": "is decorated with", "words": ["decorated with", "decorated in", "is surrounded by", "is decorated with", "is white with", "is decorated in", "adorned with"], "represent_word_sim": 0.9909628827861953}, "85": {"represent_word": "peeling", "words": ["peeling"], "represent_word_sim": 0.9999999926560326}, "86": {"represent_word": "set on", "words": ["set on", "set in", "set with", "set up with"], "represent_word_sim": 0.9753937297508728}, "87": {"represent_word": "to be", "words": ["appears to be", "to be", "be"], "represent_word_sim": 0.9869738964404312}, "88": {"represent_word": "helping", "words": ["helping"], "represent_word_sim": 0.9999999936191454}, "89": {"represent_word": "stall with", "words": ["stall with", "stall in"], "represent_word_sim": 0.9920376770862089}, "90": {"represent_word": "enter", "words": ["enter"], "represent_word_sim": 1.0000000206572404}, "91": {"represent_word": "wheeled", "words": ["wheeled"], "represent_word_sim": 1.0000000037880281}, "92": {"represent_word": "overlooking", "words": ["overlooking"], "represent_word_sim": 0.9999999690605809}, "93": {"represent_word": "chopped", "words": ["chopped"], "represent_word_sim": 1.0000000095072759}, "94": {"represent_word": "featuring", "words": ["featuring", "features"], "represent_word_sim": 0.970075749584809}, "95": {"represent_word": "covered", "words": ["covered"], "represent_word_sim": 0.9999999763507734}, "96": {"represent_word": "boarding", "words": ["boarding"], "represent_word_sim": 1.0000000233571298}, "97": {"represent_word": "drawn", "words": ["drawn"], "represent_word_sim": 0.9999999733541186}, "98": {"represent_word": "stirring", "words": ["stirring"], "represent_word_sim": 0.9999999253268149}, "99": {"represent_word": "drives", "words": ["drives"], "represent_word_sim": 1.0000000000428595}, "100": {"represent_word": "exiting", "words": ["exiting"], "represent_word_sim": 0.9999999730942087}, "101": {"represent_word": "mounted on", "words": ["mounted on", "mounted", "mounted to"], "represent_word_sim": 0.9809293566742406}, "102": {"represent_word": "sitting near", "words": ["sitting behind", "sitting", "sits near", "sitting near", "sits"], "represent_word_sim": 0.9512553015011299}, "103": {"represent_word": "preparing", "words": ["preparing", "prepare", "prepares", "are preparing", "is preparing"], "represent_word_sim": 0.9799628293302745}, "104": {"represent_word": "between", "words": ["between", "in between"], "represent_word_sim": 0.9822778651074812}, "105": {"represent_word": "about", "words": ["about"], "represent_word_sim": 0.9999999947972132}, "106": {"represent_word": "hit", "words": ["to hit", "hit"], "represent_word_sim": 0.98527722875508}, "107": {"represent_word": "measuring", "words": ["measuring"], "represent_word_sim": 1.0000000289059825}, "108": {"represent_word": "getting off", "words": ["getting", "off", "getting off"], "represent_word_sim": 0.9775074632568764}, "109": {"represent_word": "reading", "words": ["reading"], "represent_word_sim": 0.9999999831990484}, "110": {"represent_word": "stained", "words": ["stained"], "represent_word_sim": 0.9999999635020264}, "111": {"represent_word": "matching", "words": ["matching"], "represent_word_sim": 0.9999999986476524}, "112": {"represent_word": "looking out", "words": ["looking out", "out", "out of", "looking out of"], "represent_word_sim": 0.9681283223430056}, "113": {"represent_word": "sitting at", "words": ["sitting at", "sits at", "sit at", "is sitting at", "are sitting at"], "represent_word_sim": 0.9849821317891885}, "114": {"represent_word": "stands next to", "words": ["stands in", "stands behind", "stands next to", "standing next to", "stands on", "stands at", "stands near", "stand next to", "holds up", "stands with"], "represent_word_sim": 0.9765283380483233}, "115": {"represent_word": "show", "words": ["show", "shows"], "represent_word_sim": 0.9749831296065782}, "116": {"represent_word": "ride", "words": ["ride"], "represent_word_sim": 0.9999999749535647}, "117": {"represent_word": "is sitting on", "words": ["sitting on", "is eating", "lies on", "is sitting on", "while sitting on", "is standing on", "sleeping on", "is sleeping on", "are sitting on", "lying on", "is lying on"], "represent_word_sim": 0.9857309916353871}, "118": {"represent_word": "approaching", "words": ["approaching"], "represent_word_sim": 1.0000000264241398}, "119": {"represent_word": "includes", "words": ["includes", "including"], "represent_word_sim": 0.9741070251549364}, "120": {"represent_word": "brushing", "words": ["brushing"], "represent_word_sim": 0.9999999917075513}, "121": {"represent_word": "sticking", "words": ["sticking"], "represent_word_sim": 1.0000000139663126}, "122": {"represent_word": "enjoying", "words": ["enjoying"], "represent_word_sim": 1.00000006380067}, "123": {"represent_word": "inside of", "words": ["inside", "inside of", "from inside", "sitting inside of"], "represent_word_sim": 0.9801974857708735}, "124": {"represent_word": "besides", "words": ["besides"], "represent_word_sim": 1.000000044338787}, "125": {"represent_word": "cleaning", "words": ["cleaning"], "represent_word_sim": 1.0000000010633951}, "126": {"represent_word": "onto", "words": ["onto", "holding onto"], "represent_word_sim": 0.9796924684905748}, "127": {"represent_word": "touching", "words": ["touching"], "represent_word_sim": 1.0000000028701612}, "128": {"represent_word": "toned", "words": ["toned"], "represent_word_sim": 0.9999999662506052}, "129": {"represent_word": "flying", "words": ["flying", "is flying"], "represent_word_sim": 0.9902371258842514}, "130": {"represent_word": "riding on", "words": ["are riding", "riding in", "is riding", "riding on", "is riding on", "while riding", "to ride", "riding through", "are riding on"], "represent_word_sim": 0.9793462350815457}, "131": {"represent_word": "tiled", "words": ["tiled"], "represent_word_sim": 0.999999966984321}, "132": {"represent_word": "to cross", "words": ["waiting to cross", "to cross"], "represent_word_sim": 0.9909074332628758}, "133": {"represent_word": "needs", "words": ["needs"], "represent_word_sim": 0.9999999983251852}, "134": {"represent_word": "colored", "words": ["colored"], "represent_word_sim": 0.9999999826847081}, "135": {"represent_word": "sitting below", "words": ["below", "sitting above", "sitting below"], "represent_word_sim": 0.9799369340275865}, "136": {"represent_word": "painted", "words": ["painted", "painted on"], "represent_word_sim": 0.9799676036345815}, "137": {"represent_word": "shaving", "words": ["shaving"], "represent_word_sim": 1.0000000350429297}, "138": {"represent_word": "feeding", "words": ["feeding"], "represent_word_sim": 1.0000000251545875}, "139": {"represent_word": "following", "words": ["following"], "represent_word_sim": 0.999999976925406}, "140": {"represent_word": "watches", "words": ["watches", "watch"], "represent_word_sim": 0.9689842193509733}, "141": {"represent_word": "mixing", "words": ["mixing"], "represent_word_sim": 0.999999859763036}, "142": {"represent_word": "lit by", "words": ["illuminated by", "lit by", "lit"], "represent_word_sim": 0.9821486870834731}, "143": {"represent_word": "atop", "words": ["atop"], "represent_word_sim": 1.0000000151686061}, "144": {"represent_word": "pushing", "words": ["pushing"], "represent_word_sim": 0.9999999808453182}, "145": {"represent_word": "before", "words": ["before", "after"], "represent_word_sim": 0.9517697320845792}, "146": {"represent_word": "surrounding", "words": ["surrounding"], "represent_word_sim": 0.999999910337841}, "147": {"represent_word": "pouring", "words": ["pouring"], "represent_word_sim": 1.0000000213598115}, "148": {"represent_word": "taking", "words": ["taking", "takes", "take"], "represent_word_sim": 0.9768876949513803}, "149": {"represent_word": "observing", "words": ["observing"], "represent_word_sim": 0.999999981622137}, "150": {"represent_word": "taken of", "words": ["taken from", "taken of"], "represent_word_sim": 0.9740279553866262}, "151": {"represent_word": "petting", "words": ["petting"], "represent_word_sim": 1.000000001261797}, "152": {"represent_word": "facing", "words": ["facing"], "represent_word_sim": 1.000000035111296}, "153": {"represent_word": "talking on", "words": ["talking on", "is talking on", "while talking on", "talking to", "is using"], "represent_word_sim": 0.9746969059004281}, "154": {"represent_word": "moving", "words": ["moving"], "represent_word_sim": 0.9999999488056863}, "155": {"represent_word": "open", "words": ["open"], "represent_word_sim": 1.0000000440042898}, "156": {"represent_word": "standing on", "words": ["standing", "stand on", "standing at", "standing on", "standing behind", "standing near", "are standing on", "standing over"], "represent_word_sim": 0.9753679669744344}, "157": {"represent_word": "play", "words": ["play"], "represent_word_sim": 0.9999999801197121}, "158": {"represent_word": "going down", "words": ["down", "is going down", "going down", "coming down"], "represent_word_sim": 0.9839568535461998}, "159": {"represent_word": "containing", "words": ["contains", "containing"], "represent_word_sim": 0.9825484702908952}, "160": {"represent_word": "all over", "words": ["all over"], "represent_word_sim": 0.9999999742140558}, "161": {"represent_word": "going around", "words": ["going around"], "represent_word_sim": 0.9999999329780261}, "162": {"represent_word": "using", "words": ["using", "while using"], "represent_word_sim": 0.9825833322552526}, "163": {"represent_word": "displays", "words": ["displays"], "represent_word_sim": 1.0000000009047056}, "164": {"represent_word": "run down", "words": ["run down"], "represent_word_sim": 0.9999999509696241}, "165": {"represent_word": "dressed as", "words": ["dressed as", "dressed in"], "represent_word_sim": 0.9840683761741809}, "166": {"represent_word": "is pictured in", "words": ["is pictured in", "pictured in", "seen in", "is seen in"], "represent_word_sim": 0.9818726343888059}, "167": {"represent_word": "throwing", "words": ["throwing"], "represent_word_sim": 1.000000000036924}, "168": {"represent_word": "during", "words": ["during"], "represent_word_sim": 0.9999999729612618}, "169": {"represent_word": "without", "words": ["without"], "represent_word_sim": 0.9999999705231977}, "170": {"represent_word": "leaving", "words": ["leaving"], "represent_word_sim": 1.0000000276405696}, "171": {"represent_word": "eat", "words": ["eat"], "represent_word_sim": 1.0000000087517151}, "172": {"represent_word": "coming in for", "words": ["coming in for"], "represent_word_sim": 1.0000000215922733}, "173": {"represent_word": "does", "words": ["does"], "represent_word_sim": 1.0000000812237033}, "174": {"represent_word": "made of", "words": ["made of", "made out of", "made"], "represent_word_sim": 0.9758255710150461}, "175": {"represent_word": "placing", "words": ["placing"], "represent_word_sim": 1.0000000174337489}, "176": {"represent_word": "flies", "words": ["flies"], "represent_word_sim": 0.9999999690913253}, "177": {"represent_word": "across", "words": ["across", "across from"], "represent_word_sim": 0.9730223597156148}, "178": {"represent_word": "crossing", "words": ["crossing"], "represent_word_sim": 1.0000000276995802}, "179": {"represent_word": "built into", "words": ["into", "built into"], "represent_word_sim": 0.9745252868342501}, "180": {"represent_word": "strapped to", "words": ["strapped to"], "represent_word_sim": 1.0000000115179062}, "181": {"represent_word": "covered in", "words": ["wrapped in", "covered with", "covering", "covered in", "is covered with", "is covered in"], "represent_word_sim": 0.9856405327165467}, "182": {"represent_word": "leading", "words": ["leading"], "represent_word_sim": 1.0000000193782919}, "183": {"represent_word": "jumping in", "words": ["jumping in"], "represent_word_sim": 1.000000000955553}, "184": {"represent_word": "reflected in", "words": ["is reflected in", "reflected in"], "represent_word_sim": 0.9951373995848423}, "185": {"represent_word": "attached to", "words": ["locked to", "attached to", "tied to", "connected to", "is attached to"], "represent_word_sim": 0.9771612777222938}, "186": {"represent_word": "past", "words": ["past", "driving past"], "represent_word_sim": 0.9775932006007977}, "187": {"represent_word": "through", "words": ["through", "looking through", "seen through", "going through"], "represent_word_sim": 0.9670773704053305}, "188": {"represent_word": "alongside", "words": ["alongside"], "represent_word_sim": 1.000000025052361}, "189": {"represent_word": "making", "words": ["making", "is making"], "represent_word_sim": 0.9861472620090456}, "190": {"represent_word": "passing", "words": ["passing"], "represent_word_sim": 0.9999999910175987}, "191": {"represent_word": "smiling", "words": ["smiling"], "represent_word_sim": 0.9999999101499693}, "192": {"represent_word": "posing with", "words": ["poses with", "posing with", "posing on"], "represent_word_sim": 0.9814547465411845}, "193": {"represent_word": "cluttered with", "words": ["is cluttered with", "cluttered with"], "represent_word_sim": 0.9964532561262344}, "194": {"represent_word": "have", "words": ["have"], "represent_word_sim": 0.9999999786483234}, "195": {"represent_word": "walks", "words": ["walks"], "represent_word_sim": 1.0000000140502243}, "196": {"represent_word": "says", "words": ["says"], "represent_word_sim": 0.9999999841428393}, "197": {"represent_word": "are doing", "words": ["are doing"], "represent_word_sim": 1.0000000633079227}, "198": {"represent_word": "having", "words": ["having"], "represent_word_sim": 0.9999999809533074}, "199": {"represent_word": "land on", "words": ["land on"], "represent_word_sim": 1.000000008108801}, "200": {"represent_word": "sink", "words": ["sink"], "represent_word_sim": 0.9999999788388719}, "201": {"represent_word": "showing", "words": ["showing"], "represent_word_sim": 1.0000000335832222}, "202": {"represent_word": "hangs on", "words": ["hanging on", "hangs on"], "represent_word_sim": 0.9911639473658364}, "203": {"represent_word": "paneled", "words": ["paneled"], "represent_word_sim": 0.9999999739486528}, "204": {"represent_word": "performing", "words": ["performing"], "represent_word_sim": 0.9999999853317205}, "205": {"represent_word": "taking off from", "words": ["taking off from"], "represent_word_sim": 0.9999999802132835}, "206": {"represent_word": "is parked in", "words": ["is parked at", "parked in", "is parked in", "stopped in", "is parked on", "stopped on", "are parked in"], "represent_word_sim": 0.9823446361928176}, "207": {"represent_word": "wears", "words": ["wears"], "represent_word_sim": 0.9999999801019972}, "208": {"represent_word": "standing under", "words": ["standing under"], "represent_word_sim": 1.0000000236898174}, "209": {"represent_word": "working on", "words": ["working at", "working in", "working on", "is working on", "is working in"], "represent_word_sim": 0.9725384355787268}}